Metadata-Version: 1.0
Name: django-chatrooms
Version: 1.1adev
Summary: A django app providing reverse-ajax chat rooms
Home-page: https://github.com/qubird/django-chatrooms
Author: Vincenzo E. Antignano (@qubird)
Author-email: UNKNOWN
License: GPL
Keywords: django chat ajax
Platform: UNKNOWN
Classifier: Programming Language :: Python
Classifier: Framework :: Django
Classifier: Intended Audience :: Developers
Classifier: Development Status :: 3 - Alpha
Classifier: License :: OSI Approved :: GNU General Public License (GPL)
